bioportal_mcp/__init__.py
bioportal_mcp/__main__.py
bioportal_mcp/main.py
bioportal_mcp-0.1.0.dist-info/METADATA
bioportal_mcp-0.1.0.dist-info/WHEEL
bioportal_mcp-0.1.0.dist-info/entry_points.txt
bioportal_mcp-0.1.0.dist-info/RECORD
