Metadata-Version: 2.4
Name: bioportal-mcp
Version: 0.1.0
Summary: A model context protocol (MCP) for interacting with Bioportal
Project-URL: Homepage, https://github.com/ncbo/bioportal-mcp
Project-URL: Bug Tracker, https://github.com/ncbo/bioportal-mcp/issues
Author-email: Justin Reese <justaddcoffee@gmail.com>, "J. Harry Caufield" <jhc@lbl.gov>
Requires-Python: <4.0,>=3.11
Requires-Dist: fastmcp>=2.7.1
Requires-Dist: requests>=2.32.4
